liteaccess/__init__.py
liteaccess/liteCNS.py
liteaccess/liteaccess.py
liteaccess-3.3.0.dist-info/METADATA
liteaccess-3.3.0.dist-info/WHEEL
liteaccess-3.3.0.dist-info/licenses/LICENSE
liteaccess-3.3.0.dist-info/RECORD
