Metadata-Version: 2.3
Name: liteaccess
Version: 3.3.0
Summary: Access to Process Variables, served by liteServer
Project-URL: Homepage, https://github.com/ASukhanov/liteAccess
Project-URL: Bug Tracker, https://github.com/ASukhanov/liteAccess/issues
Author-email: Andrei Sukhanov <cyxandr@gmail.com>
License-File: LICENSE
Classifier: License :: OSI Approved :: MIT License
Classifier: Operating System :: OS Independent
Classifier: Programming Language :: Python :: 3
Requires-Python: >=3.7
Requires-Dist: cbor2
